odoo/addons/product_supplierinfo_for_customer_sale_blanket_order/README.rst
odoo/addons/product_supplierinfo_for_customer_sale_blanket_order/__init__.py
odoo/addons/product_supplierinfo_for_customer_sale_blanket_order/__manifest__.py
odoo/addons/product_supplierinfo_for_customer_sale_blanket_order/i18n/es.po
odoo/addons/product_supplierinfo_for_customer_sale_blanket_order/i18n/it.po
odoo/addons/product_supplierinfo_for_customer_sale_blanket_order/i18n/product_supplierinfo_for_customer_sale_blanket_order.pot
odoo/addons/product_supplierinfo_for_customer_sale_blanket_order/models/__init__.py
odoo/addons/product_supplierinfo_for_customer_sale_blanket_order/models/sale_blanket_order_line.py
odoo/addons/product_supplierinfo_for_customer_sale_blanket_order/readme/CONTRIBUTORS.rst
odoo/addons/product_supplierinfo_for_customer_sale_blanket_order/readme/DESCRIPTION.rst
odoo/addons/product_supplierinfo_for_customer_sale_blanket_order/static/description/icon.png
odoo/addons/product_supplierinfo_for_customer_sale_blanket_order/static/description/index.html
odoo/addons/product_supplierinfo_for_customer_sale_blanket_order/tests/__init__.py
odoo/addons/product_supplierinfo_for_customer_sale_blanket_order/tests/test_product_supplierinfo_for_customer_sale_blanket_order.py
odoo/addons/product_supplierinfo_for_customer_sale_blanket_order/views/sale_blanket_order_line_views.xml
odoo/addons/product_supplierinfo_for_customer_sale_blanket_order/views/sale_blanket_order_views.xml
odoo/addons/product_supplierinfo_for_customer_sale_blanket_order/wizard/__init__.py
odoo/addons/product_supplierinfo_for_customer_sale_blanket_order/wizard/create_sale_orders.py
odoo14_addon_product_supplierinfo_for_customer_sale_blanket_order-14.0.1.0.1.dev6.dist-info/METADATA
odoo14_addon_product_supplierinfo_for_customer_sale_blanket_order-14.0.1.0.1.dev6.dist-info/WHEEL
odoo14_addon_product_supplierinfo_for_customer_sale_blanket_order-14.0.1.0.1.dev6.dist-info/top_level.txt
odoo14_addon_product_supplierinfo_for_customer_sale_blanket_order-14.0.1.0.1.dev6.dist-info/RECORD
